{
  "$schema": "https://dl.viam.dev/module.schema.json",
  "module_id": "hunter:yoobic",
  "visibility": "private",
  "url": "https://github.com/hunter-volkman/viam-yoobic",
  "description": "YOOBIC integration module for operational workflows",
  "models": [
    {
      "api": "rdk:component:sensor",
      "model": "hunter:yoobic:mission",
      "short_description": "Mission management via YOOBIC API",
      "markdown_link": "README.md#mission-model"
    }
  ],
  "applications": null,
  "markdown_link": "README.md",
  "entrypoint": "./run.sh",
  "first_run": "./setup.sh",
  "build": {
    "build": "./build.sh",
    "setup": "./setup.sh",
    "path": "dist/archive.tar.gz",
    "arch": [
      "linux/amd64",
      "linux/arm64"
    ]
  }
}
